tnsa_standard/__init__.py
tnsa_standard/elysium_ContextAwareSymbolicReasoning.py
tnsa_standard/elysium_CrossModalityAttention.py
tnsa_standard/elysium_DeliberationMechanism.py
tnsa_standard/elysium_EnhancedReasoningModule.py
tnsa_standard/elysium_FinalLinearSoftmaxLayer.py
tnsa_standard/elysium_LossFunctionOptimization.py
tnsa_standard/elysium_MemoryAdaptiveAttentionImplementation.py
tnsa_standard/elysium_MetaLearningAdaptiveLearning.py
tnsa_standard/elysium_MultiHeadSelfAttentionMechanism.py
tnsa_standard/elysium_OutputDeliberation.py
tnsa_standard/elysium_ProblemSpecificReasoningModule.py
tnsa_standard/elysium_SpecializedKnowledgeIntegrationImplementation.py
tnsa_standard/elysium_TrainerAndParellelizer.py
tnsa_standard/elysium_Transformer.py
tnsa_standard/elysium_multimodal.py
tnsa_standard/import_all.py
tnsaaiE-2.1.56.5.dist-info/METADATA
tnsaaiE-2.1.56.5.dist-info/WHEEL
tnsaaiE-2.1.56.5.dist-info/top_level.txt
tnsaaiE-2.1.56.5.dist-info/RECORD
