Metadata-Version: 2.1
Name: tnsaaiE
Version: 2.1.56.5
Summary: TNSA Standard is a MuiltiModal Development Framework developed by TNSA AI 
Home-page: https://tnsaai.github.io/home/
Author: TNSA Artificial Intelligence
Author-email: tnsa.company@gmail.com
Classifier: Programming Language :: Python :: 3
Classifier: Operating System :: OS Independent
Requires-Python: >=3.6
